{
  "version": "0.1.0",
  "name": "multiversed_dapp",
  "instructions": [
    {
      "name": "initializeAccounts",
      "accounts": [
        {
          "name": "stakingPool",
          "isMut": true,
          "isSigner": false
        },
        {
          "name": "poolEscrowAccount",
          "isMut": true,
          "isSigner": false
        },
        {
          "name": "mint",
          "isMut": false,
          "isSigner": false
        },
        {
          "name": "admin",
          "isMut": true,
          "isSigner": true
        },
        {
          "name": "systemProgram",
          "isMut": false,
          "isSigner": false
        },
        {
          "name": "tokenProgram",
          "isMut": false,
          "isSigner": false
        }
      ],
      "args": []
    },
    {
      "name": "stake",
      "accounts": [
        {
          "name": "user",
          "isMut": true,
          "isSigner": true
        },
        {
          "name": "stakingPool",
          "isMut": true,
          "isSigner": false
        },
        {
          "name": "userStakingAccount",
          "isMut": true,
          "isSigner": false
        },
        {
          "name": "userTokenAccount",
          "isMut": true,
          "isSigner": false
        },
        {
          "name": "poolEscrowAccount",
          "isMut": true,
          "isSigner": false
        },
        {
          "name": "mint",
          "isMut": true,
          "isSigner": false
        },
        {
          "name": "tokenProgram",
          "isMut": false,
          "isSigner": false
        },
        {
          "name": "systemProgram",
          "isMut": false,
          "isSigner": false
        }
      ],
      "args": [
        {
          "name": "amount",
          "type": "u64"
        },
        {
          "name": "lockDuration",
          "type": "i64"
        }
      ]
    },
    {
      "name": "unstake",
      "accounts": [
        {
          "name": "user",
          "isMut": true,
          "isSigner": true
        },
        {
          "name": "stakingPool",
          "isMut": true,
          "isSigner": false
        },
        {
          "name": "userStakingAccount",
          "isMut": true,
          "isSigner": false
        },
        {
          "name": "userTokenAccount",
          "isMut": true,
          "isSigner": false
        },
        {
          "name": "poolEscrowAccount",
          "isMut": true,
          "isSigner": false
        },
        {
          "name": "mint",
          "isMut": true,
          "isSigner": false
        },
        {
          "name": "tokenProgram",
          "isMut": false,
          "isSigner": false
        }
      ],
      "args": []
    },
    {
      "name": "createTournamentPool",
      "accounts": [
        {
          "name": "tournamentPool",
          "isMut": true,
          "isSigner": false
        },
        {
          "name": "poolEscrowAccount",
          "isMut": true,
          "isSigner": false
        },
        {
          "name": "mint",
          "isMut": false,
          "isSigner": false
        },
        {
          "name": "admin",
          "isMut": true,
          "isSigner": true
        },
        {
          "name": "systemProgram",
          "isMut": false,
          "isSigner": false
        },
        {
          "name": "tokenProgram",
          "isMut": false,
          "isSigner": false
        }
      ],
      "args": [
        {
          "name": "tournamentId",
          "type": "string"
        },
        {
          "name": "entryFee",
          "type": "u64"
        },
        {
          "name": "maxParticipants",
          "type": "u16"
        },
        {
          "name": "endTime",
          "type": "i64"
        }
      ]
    },
    {
      "name": "registerForTournament",
      "accounts": [
        {
          "name": "user",
          "isMut": true,
          "isSigner": true
        },
        {
          "name": "tournamentPool",
          "isMut": true,
          "isSigner": false
        },
        {
          "name": "registrationAccount",
          "isMut": true,
          "isSigner": false
        },
        {
          "name": "userTokenAccount",
          "isMut": true,
          "isSigner": false
        },
        {
          "name": "poolEscrowAccount",
          "isMut": true,
          "isSigner": false
        },
        {
          "name": "mint",
          "isMut": true,
          "isSigner": false
        },
        {
          "name": "tokenProgram",
          "isMut": false,
          "isSigner": false
        },
        {
          "name": "systemProgram",
          "isMut": false,
          "isSigner": false
        }
      ],
      "args": [
        {
          "name": "tournamentId",
          "type": "string"
        }
      ]
    },
    {
      "name": "initializeRevenuePool",
      "accounts": [
        {
          "name": "revenuePool",
          "isMut": true,
          "isSigner": false
        },
        {
          "name": "revenueEscrowAccount",
          "isMut": true,
          "isSigner": false
        },
        {
          "name": "mint",
          "isMut": false,
          "isSigner": false
        },
        {
          "name": "admin",
          "isMut": true,
          "isSigner": true
        },
        {
          "name": "systemProgram",
          "isMut": false,
          "isSigner": false
        },
        {
          "name": "tokenProgram",
          "isMut": false,
          "isSigner": false
        }
      ],
      "args": []
    },
    {
      "name": "initializePrizePool",
      "accounts": [
        {
          "name": "prizePool",
          "isMut": true,
          "isSigner": false
        },
        {
          "name": "tournamentPool",
          "isMut": true,
          "isSigner": false
        },
        {
          "name": "prizeEscrowAccount",
          "isMut": true,
          "isSigner": false
        },
        {
          "name": "mint",
          "isMut": false,
          "isSigner": false
        },
        {
          "name": "admin",
          "isMut": true,
          "isSigner": true
        },
        {
          "name": "systemProgram",
          "isMut": false,
          "isSigner": false
        },
        {
          "name": "tokenProgram",
          "isMut": false,
          "isSigner": false
        }
      ],
      "args": [
        {
          "name": "tournamentId",
          "type": "string"
        }
      ]
    },
    {
      "name": "distributeTournamentRevenue",
      "accounts": [
        {
          "name": "admin",
          "isMut": true,
          "isSigner": true
        },
        {
          "name": "tournamentPool",
          "isMut": true,
          "isSigner": false
        },
        {
          "name": "prizePool",
          "isMut": true,
          "isSigner": false
        },
        {
          "name": "revenuePool",
          "isMut": true,
          "isSigner": false
        },
        {
          "name": "stakingPool",
          "isMut": true,
          "isSigner": false
        },
        {
          "name": "tournamentEscrowAccount",
          "isMut": true,
          "isSigner": false
        },
        {
          "name": "prizeEscrowAccount",
          "isMut": true,
          "isSigner": false
        },
        {
          "name": "revenueEscrowAccount",
          "isMut": true,
          "isSigner": false
        },
        {
          "name": "stakingEscrowAccount",
          "isMut": true,
          "isSigner": false
        },
        {
          "name": "mint",
          "isMut": true,
          "isSigner": false
        },
        {
          "name": "tokenProgram",
          "isMut": false,
          "isSigner": false
        }
      ],
      "args": [
        {
          "name": "tournamentId",
          "type": "string"
        },
        {
          "name": "prizePercentage",
          "type": "u8"
        },
        {
          "name": "revenuePercentage",
          "type": "u8"
        },
        {
          "name": "stakingPercentage",
          "type": "u8"
        },
        {
          "name": "burnPercentage",
          "type": "u8"
        }
      ]
    }
  ],
  "accounts": [
    {
      "name": "StakingPool",
      "type": {
        "kind": "struct",
        "fields": [
          {
            "name": "admin",
            "type": "publicKey"
          },
          {
            "name": "mint",
            "type": "publicKey"
          },
          {
            "name": "totalStaked",
            "type": "u64"
          },
          {
            "name": "bump",
            "type": "u8"
          }
        ]
      }
    },
    {
      "name": "UserStakingAccount",
      "type": {
        "kind": "struct",
        "fields": [
          {
            "name": "owner",
            "type": "publicKey"
          },
          {
            "name": "stakedAmount",
            "type": "u64"
          },
          {
            "name": "stakeTimestamp",
            "type": "i64"
          },
          {
            "name": "lockDuration",
            "type": "i64"
          }
        ]
      }
    },
    {
      "name": "TournamentPool",
      "type": {
        "kind": "struct",
        "fields": [
          {
            "name": "admin",
            "type": "publicKey"
          },
          {
            "name": "mint",
            "type": "publicKey"
          },
          {
            "name": "tournamentId",
            "type": {
              "array": [
                "u8",
                10
              ]
            }
          },
          {
            "name": "entryFee",
            "type": "u64"
          },
          {
            "name": "totalFunds",
            "type": "u64"
          },
          {
            "name": "participantCount",
            "type": "u16"
          },
          {
            "name": "maxParticipants",
            "type": "u16"
          },
          {
            "name": "endTime",
            "type": "i64"
          },
          {
            "name": "isActive",
            "type": "bool"
          },
          {
            "name": "bump",
            "type": "u8"
          }
        ]
      }
    },
    {
      "name": "RegistrationRecord",
      "type": {
        "kind": "struct",
        "fields": [
          {
            "name": "user",
            "type": "publicKey"
          },
          {
            "name": "tournamentPool",
            "type": "publicKey"
          },
          {
            "name": "isInitialized",
            "type": "bool"
          },
          {
            "name": "registrationTime",
            "type": "i64"
          },
          {
            "name": "bump",
            "type": "u8"
          }
        ]
      }
    },
    {
      "name": "PrizePool",
      "type": {
        "kind": "struct",
        "fields": [
          {
            "name": "admin",
            "type": "publicKey"
          },
          {
            "name": "tournamentPool",
            "type": "publicKey"
          },
          {
            "name": "mint",
            "type": "publicKey"
          },
          {
            "name": "tournamentId",
            "type": {
              "array": [
                "u8",
                10
              ]
            }
          },
          {
            "name": "totalFunds",
            "type": "u64"
          },
          {
            "name": "distributed",
            "type": "bool"
          },
          {
            "name": "bump",
            "type": "u8"
          }
        ]
      }
    },
    {
      "name": "RevenuePool",
      "type": {
        "kind": "struct",
        "fields": [
          {
            "name": "admin",
            "type": "publicKey"
          },
          {
            "name": "mint",
            "type": "publicKey"
          },
          {
            "name": "totalFunds",
            "type": "u64"
          },
          {
            "name": "lastDistribution",
            "type": "i64"
          },
          {
            "name": "bump",
            "type": "u8"
          }
        ]
      }
    }
  ],
  "types": [],
  "errors": [
    {
      "code": 6000,
      "name": "InsufficientFunds",
      "msg": "Insufficient funds to register for this tournament."
    },
    {
      "code": 6001,
      "name": "TournamentFull",
      "msg": "Tournament is full."
    },
    {
      "code": 6002,
      "name": "TournamentEnded",
      "msg": "Tournament has ended."
    },
    {
      "code": 6003,
      "name": "TournamentNotActive",
      "msg": "Tournament is not active."
    },
    {
      "code": 6004,
      "name": "AlreadyRegistered",
      "msg": "User is already registered for this tournament."
    },
    {
      "code": 6005,
      "name": "InvalidEntryFee",
      "msg": "Invalid entry fee."
    },
    {
      "code": 6006,
      "name": "InvalidMaxParticipants",
      "msg": "Invalid maximum participants."
    },
    {
      "code": 6007,
      "name": "InvalidEndTime",
      "msg": "Invalid end time."
    },
    {
      "code": 6008,
      "name": "Unauthorized",
      "msg": "Unauthorized action."
    },
    {
      "code": 6009,
      "name": "InvalidWinnerData",
      "msg": "Invalid winner data."
    },
    {
      "code": 6010,
      "name": "InvalidWinnerPercentages",
      "msg": "Winner percentages must sum to 100."
    },
    {
      "code": 6011,
      "name": "InvalidPercentages",
      "msg": "Distribution percentages must sum to 100."
    },
    {
      "code": 6012,
      "name": "AlreadyInitialized",
      "msg": "Staking Pool already initialized by this admin"
    },
    {
      "code": 6013,
      "name": "InsufficientStakedBalance",
      "msg": "Insufficient staked balance"
    },
    {
      "code": 6014,
      "name": "UnauthorizedAccess",
      "msg": "Unauthorized access"
    },
    {
      "code": 6015,
      "name": "MathOverflow",
      "msg": "Math overflow occurred"
    },
    {
      "code": 6016,
      "name": "StakeLockActive",
      "msg": "Unstaking is locked"
    },
    {
      "code": 6017,
      "name": "InvalidLockDuration",
      "msg": "Invalid Lock Duration, Must be 1, 3, 6 or 12 months"
    }
  ],
  "metadata": {
    "address": "GSV3Qje19X3NTxc5uxhKw28uoadpZED5Siqd4tGVZ7x4"
  }
}